{
  "products": [
    {
      "name": "Wellsley Farms Mini Cucumbers, 18 oz.",
      "price": "$2.79",
      "unit_price": "$2.48/lb"
    },
    {
      "name": "Wellsley Farms Mixed Peppers, 4 ct.",
      "price": "$4.49",
      "unit_price": null
    },
    {
      "name": "Wellsley Farms Yellow Onions, 3 lbs.",
      "price": "$2.49",
      "unit_price": "$0.83/lb"
    },
    {
      "name": "Wellsley Farms Idaho Potatoes, 5 lbs.",
      "price": "$2.99",
      "unit_price": "$0.60/lb"
    },
    {
      "name": "Wellsley Farms Organic Baby Cut Carrots, 2 lbs.",
      "price": "$3.49",
      "unit_price": "$1.75/lb"
    },
    {
      "name": "Wellsley Farms Organic Whole Carrots, 5 lbs.",
      "price": "$5.29",
      "unit_price": "$1.06/lb"
    },
    {
      "name": "Wellsley Farms Brussels Sprouts, 2 lbs.",
      "price": "$5.29",
      "unit_price": "$2.65/lb"
    },
    {
      "name": "Mixed Zucchini & Yellow Squash, 2 lbs.",
      "price": "$4.99",
      "unit_price": "$2.50/lb"
    },
    {
      "name": "Wellsley Farms Sweet Potatoes, 3 lbs.",
      "price": "$2.89",
      "unit_price": "$0.96/lb"
    },
    {
      "name": "Green Onions, 10 oz.",
      "price": "$1.99",
      "unit_price": "$3.18/lb"
    },
    {
      "name": "Wellsley Farms Fresh Asparagus, 28 oz.",
      "price": "$7.99",
      "unit_price": "$4.57/lb"
    },
    {
      "name": "Fresh Green Cabbage, 1 ct.",
      "price": "$1.99",
      "unit_price": null
    },
    {
      "name": "Wellsley Farms Premium Sweet Onions, 5 lbs.",
      "price": "$6.69",
      "unit_price": "$1.34/lb"
    },
    {
      "name": "Wellsley Farms Russet Potatoes, 10 lbs.",
      "price": "$4.99",
      "unit_price": "$0.50/lb"
    },
    {
      "name": "Baby-Cut Carrots, 32 oz.",
      "price": "$2.79",
      "unit_price": "$1.40/lb"
    },
    {
      "name": "Broccoli Florets, 2 lbs.",
      "price": "$4.69",
      "unit_price": "$2.35/lb"
    },
    {
      "name": "Wellsley Farms English Seedless Cucumbers, 2 ct.",
      "price": "$2.59",
      "unit_price": null
    },
    {
      "name": "Pero Snipped Green Beans, 2 lbs.",
      "price": "$5.99",
      "unit_price": "$3.00/lb"
    },
    {
      "name": "Wellsley Farms Zucchini Squash, 24 oz.",
      "price": "$3.99",
      "unit_price": "$2.66/lb"
    },
    {
      "name": "Sleeved Celery Stalk",
      "price": "$1.69",
      "unit_price": null
    },
    {
      "name": "Wellsley Farms Organic Russet Potatoes, 3 lbs.",
      "price": "$3.49",
      "unit_price": "$1.16/lb"
    },
    {
      "name": "Wellsley Farms Organic Baby Spinach, 16 oz.",
      "price": "$4.99",
      "unit_price": "$4.99/lb"
    },
    {
      "name": "Wellsley Farms Sliced Mushrooms, 20 oz.",
      "price": "$4.29",
      "unit_price": "$3.43/lb"
    },
    {
      "name": "WP Rawl Farms Bagged Organic Kale, 12 oz.",
      "price": "$3.49",
      "unit_price": "$4.65/lb"
    },
    {
      "name": "Wellsley Farms Caesar Chopped Salad Kit, 11.15 oz.",
      "price": "$3.49",
      "unit_price": "$5.01/lb"
    },
    {
      "name": "Wellsley Farms Red Potatoes, 10 lbs.",
      "price": "$7.49",
      "unit_price": "$0.75/lb"
    },
    {
      "name": "Roma Tomatoes, 3 lbs.",
      "price": "$5.99",
      "unit_price": "$2.00/lb"
    },
    {
      "name": "Romaine Lettuce Hearts, 6 ct.",
      "price": "$5.99",
      "unit_price": null
    },
    {
      "name": "Iceberg Lettuce, 1 ct.",
      "price": "$1.99",
      "unit_price": null
    },
    {
      "name": "Premium Fresh Whole Garlic, 24 oz.",
      "price": "$5.39",
      "unit_price": "$3.59/lb"
    },
    {
      "name": "The Little Potato Co. Little Duos, 3 lbs.",
      "price": "$4.99",
      "unit_price": "$1.66/lb"
    },
    {
      "name": "Wellsley Farms Fresh Red Bell Pepper, 4 ct.",
      "price": "$4.49",
      "unit_price": null
    },
    {
      "name": "Spice World Fresh Peeled Garlic Cloves, 1 lb.",
      "price": "$3.99",
      "unit_price": "$3.99/lb"
    },
    {
      "name": "Wellsley Farms Fresh Baby Bella Whole Mushrooms, 24 oz.",
      "price": "$5.29",
      "unit_price": "$3.53/lb"
    },
    {
      "name": "Sunset Lollipeppers, Seedless Mini Peppers, 1.5 lbs.",
      "price": "$4.99",
      "unit_price": "$3.33/lb"
    },
    {
      "name": "Organic Sweet Potatoes, 3 lbs.",
      "price": "$4.29",
      "unit_price": "$1.43/lb"
    },
    {
      "name": "Wellsley Farms Organic Baby Arugula, 5 oz.",
      "price": "$2.99",
      "unit_price": "$9.57/lb"
    },
    {
      "name": "Wellsley Farms Yellow Potatoes, 10 lbs.",
      "price": "$7.49",
      "unit_price": "$0.75/lb"
    },
    {
      "name": "Cauliflower Florets, 2 lbs.",
      "price": "$5.49",
      "unit_price": "$2.75/lb"
    },
    {
      "name": "Little Leaf Farms Baby Crispy Green Leaf Lettuce, 8 oz.",
      "price": "$4.49",
      "unit_price": "$8.98/lb"
    },
    {
      "name": "Fresh Express Baby Spinach, 20 oz.",
      "price": "$5.29",
      "unit_price": "$4.23/lb"
    },
    {
      "name": "Wellsley Farms Cucumber, 3 ct.",
      "price": "$2.79",
      "unit_price": null
    },
    {
      "name": "Wellsley Farms Organic Yellow Onions, 3 lbs.",
      "price": "$4.99",
      "unit_price": "$1.66/lb"
    },
    {
      "name": "Wellsley Farms Avocado Ranch Chopped Salad Kit, 12.8 oz.",
      "price": "$3.49",
      "unit_price": "$4.36/lb"
    },
    {
      "name": "Wellsley Farms Mediterranean Chopped Salad Kit, 11.01 oz.",
      "price": "$3.49",
      "unit_price": "$5.07/lb"
    },
    {
      "name": "Fresh Cilantro, 2.5 oz.",
      "price": "$2.99",
      "unit_price": "$19.14/lb"
    },
    {
      "name": "Wellsley Farms Mexican Street Corn Chopped Salad Kit, 11.62 oz.",
      "price": "$3.49",
      "unit_price": "$4.81/lb"
    },
    {
      "name": "Love Beets Cooked Beets, 35.2 oz.",
      "price": "$7.49",
      "unit_price": "$3.40/lb"
    },
    {
      "name": "Fresh Italian Parsley, 2.5 oz.",
      "price": "$1.99",
      "unit_price": "$12.74/lb"
    },
    {
      "name": "Wellsley Farms Asian Style Chopped Salad Kit, 13 oz.",
      "price": "$3.49",
      "unit_price": "$4.29/lb"
    },
    {
      "name": "Wellsley Farms Organic 50/50 Mix, 16 oz.",
      "price": "$4.99",
      "unit_price": "$4.99/lb"
    },
    {
      "name": "Wellsley Farms Sweet Kale Chopped Salad Kit, 12 oz.",
      "price": "$3.49",
      "unit_price": "$4.65/lb"
    },
    {
      "name": "Wellsley Farms Celery Sticks, 2.5 lbs.",
      "price": "$5.29",
      "unit_price": "$2.12/lb"
    },
    {
      "name": "Sunset Pop-Its Bite Sized Cucumbers, 1.5 lbs.",
      "price": "$6.49",
      "unit_price": "$4.33/lb"
    },
    {
      "name": "Flavor Bombs Cherry Tomatoes, 1.5 lbs.",
      "price": "$7.99",
      "unit_price": "$5.33/lb"
    },
    {
      "name": "Fresh Express America's Fresh Three-Color Deli Cole Slaw, 24 oz.",
      "price": "$2.49",
      "unit_price": "$1.66/lb"
    },
    {
      "name": "Wellsley Farms Everything Chopped Salad Kit, 11.57 oz.",
      "price": "$3.49",
      "unit_price": "$4.83/lb"
    },
    {
      "name": "Jalapeno Peppers, 12 oz.",
      "price": "$2.79",
      "unit_price": "$3.72/lb"
    },
    {
      "name": "Campari Tomatoes, 2 lbs.",
      "price": "$5.99",
      "unit_price": "$3.00/lb"
    },
    {
      "name": "Wellsley Farms Sweet Corn, 20 oz.",
      "price": "$7.99",
      "unit_price": "$6.39/lb"
    },
    {
      "name": "Gotham Greens Greenhouse Basil, 2 oz.",
      "price": "$3.99",
      "unit_price": "$31.92/lb"
    },
    {
      "name": "Wellsley Farms Organic Lettuce Blend, 16 oz.",
      "price": "$4.99",
      "unit_price": "$4.99/lb"
    },
    {
      "name": "Spice World Organic Whole Garlic, 5 ct.",
      "price": "$3.99",
      "unit_price": null
    },
    {
      "name": "Cubanelle Peppers, 1 lb.",
      "price": "$2.99",
      "unit_price": "$2.99/lb"
    },
    {
      "name": "Wellsley Farms Portabella Caps Mushrooms, 16 oz.",
      "price": "$4.89",
      "unit_price": "$4.89/lb"
    },
    {
      "name": "Organic Ginger, 1.75 lbs.",
      "price": "$8.99",
      "unit_price": "$5.14/lb"
    },
    {
      "name": "Wellsley Farms Organic Herb Mix, 5 oz.",
      "price": "$2.99",
      "unit_price": "$9.57/lb"
    },
    {
      "name": "Angel Sweet Grape Tomatoes, 2 lbs.",
      "price": "$6.99",
      "unit_price": "$3.50/lb"
    },
    {
      "name": "Wellsley Farms Caesar Salad with Chicken Bowl, 2 pk./6.25 oz.",
      "price": "$6.99",
      "unit_price": "$8.94/lb"
    },
    {
      "name": "Little Leaf Farms Sweet Baby Butter Leaf Lettuce, 8 oz.",
      "price": "$4.49",
      "unit_price": "$8.98/lb"
    },
    {
      "name": "Organic Romaine Lettuce Hearts, 3 ct.",
      "price": "$3.99",
      "unit_price": null
    },
    {
      "name": "Organic Mini Sweet Peppers, 1 lb.",
      "price": "$4.49",
      "unit_price": "$4.49/lb"
    },
    {
      "name": "Fresh Express Parisienne Supreme Salad Kit, 16 oz.",
      "price": "$4.99",
      "unit_price": "$4.99/lb"
    },
    {
      "name": "Wellsley Farms Maple Bourbon Bacon Chopped Salad Kit, 12.8 oz.",
      "price": "$3.49",
      "unit_price": "$4.36/lb"
    },
    {
      "name": "Collard Greens, 2 lbs.",
      "price": "$3.79",
      "unit_price": "$1.90/lb"
    },
    {
      "name": "Fresh Express Caesar Salad Kit, 19.5 oz.",
      "price": "$4.49",
      "unit_price": "$3.68/lb"
    },
    {
      "name": "Fresh Rosemary, 2.5 oz.",
      "price": "$2.99",
      "unit_price": "$19.14/lb"
    },
    {
      "name": "Wellsley Farms Apple Walnut Salad Bowl, 2 pk./5.5 oz.",
      "price": "$6.99",
      "unit_price": "$10.16/lb"
    },
    {
      "name": "Organic Celery Heart, 3 ct.",
      "price": "$4.49",
      "unit_price": null
    },
    {
      "name": "Little Leaf Farms Red & Green Leaf Lettuce, 8 oz.",
      "price": "$4.49",
      "unit_price": "$8.98/lb"
    },
    {
      "name": "Fresh Express Garden Salad, 3 lbs.",
      "price": "$5.49",
      "unit_price": "$1.83/lb"
    },
    {
      "name": "Fresh Express Chopped Romaine, 2 lbs.",
      "price": "$4.59",
      "unit_price": "$2.30/lb"
    },
    {
      "name": "Little Reds, 3 lbs.",
      "price": "$4.99",
      "unit_price": "$1.66/lb"
    },
    {
      "name": "Little Leaf Farms Romaine Leaf, 8 oz.",
      "price": "$4.49",
      "unit_price": "$8.98/lb"
    },
    {
      "name": "Fresh Express Caesar Supreme Salad Kit, 10.5 oz.",
      "price": "$3.99",
      "unit_price": "$6.08/lb"
    },
    {
      "name": "Veggie Platter, 32 oz.",
      "price": "$7.99",
      "unit_price": "$4.00/lb"
    },
    {
      "name": "Celery, 1 ct.",
      "price": "$1.99",
      "unit_price": null
    },
    {
      "name": "Olivia's Organic Diced Butternut Squash, Fresh, 32 oz.",
      "price": "$5.99",
      "unit_price": "$3.00/lb"
    },
    {
      "name": "Wellsley Farms Vidalia Sweet Onions, 5 lbs.",
      "price": "$6.69",
      "unit_price": "$1.34/lb"
    },
    {
      "name": "Poultry Blend, 3 oz.",
      "price": "$2.99",
      "unit_price": "$15.95/lb"
    },
    {
      "name": "Wild Wonders Mini Peppers, 2 lbs.",
      "price": "$5.79",
      "unit_price": "$2.90/lb"
    },
    {
      "name": "MountainKing Butter Cream Potatoes, 5 lbs.",
      "price": "$2.99",
      "unit_price": "$0.60/lb"
    },
    {
      "name": "Organic Baby Bella Mushroom, 24 oz.",
      "price": "$5.99",
      "unit_price": "$3.99/lb"
    },
    {
      "name": "Wellsley Farms Snap Peas, 18 oz.",
      "price": "$3.99",
      "unit_price": "$3.55/lb"
    },
    {
      "name": "Sunset Qukes - Teeny Tiny Cucumbers, 1.75 lbs.",
      "price": "$5.99",
      "unit_price": "$3.42/lb"
    },
    {
      "name": "Taylor Farms Cauliflower Florets, 24 oz.",
      "price": "$3.99",
      "unit_price": "$2.66/lb"
    },
    {
      "name": "Gotham Greens Basil, 2 oz.",
      "price": "$3.99",
      "unit_price": "$31.92/lb"
    },
    {
      "name": "Cello Carrots, 5 lbs.",
      "price": "$4.89",
      "unit_price": "$0.98/lb"
    },
    {
      "name": "Fresh Red Bell Pepper, 4 ct.",
      "price": "$4.49",
      "unit_price": null
    },
    {
      "name": "Portabella Mushroom Caps, 16 oz.",
      "price": "$4.89",
      "unit_price": "$4.89/lb"
    },
    {
      "name": "Large Heirloom Pumpkin, 1 ct.",
      "price": "$3.98",
      "unit_price": null
    },
    {
      "name": "Pumpkin, 1 ct.",
      "price": "$3.98",
      "unit_price": null
    },
    {
      "name": "Tanimura and Antle Artisan Romaine, 3 ct.",
      "price": "$2.99",
      "unit_price": null
    },
    {
      "name": "Sweet Potatoes, 3 lbs.",
      "price": "$2.89",
      "unit_price": "$0.96/lb"
    },
    {
      "name": "Backyard Farms Green Leaf Lettuce, 10 oz.",
      "price": "$4.49",
      "unit_price": "$7.18/lb"
    }
  ]
}